MANIFEST.in
README.md
changes.txt
license.txt
pysawit-ui.xlsm
setup.py
PySawit.egg-info/PKG-INFO
PySawit.egg-info/SOURCES.txt
PySawit.egg-info/dependency_links.txt
PySawit.egg-info/requires.txt
PySawit.egg-info/top_level.txt
docs/pysawit-model.pdf
pysawit/__init__.py
pysawit/annualweather.py
pysawit/crop.py
pysawit/energybal.py
pysawit/facade.py
pysawit/graph.py
pysawit/meteo.py
pysawit/meteostats.py
pysawit/photosyn.py
pysawit/pysawit.py
pysawit/simweather.py
pysawit/soilwater.py
pysawit/utils.py
pysawit/weatherfile.py
pysawit/examples/ini.txt
pysawit/examples/merlimau87-08.txt
pysawit/examples/output.txt