Metadata-Version: 1.2
Name: PySawit
Version: 0.0.1
Summary: Oil Palm Growth and Yield Model
Home-page: https://github.com/cbsteh/PySawit
Author: Christopher Teh Boon Sung
Author-email: christeh@yahoo.com
License: MIT
Keywords: crop soil agriculture oil palm photosynthesis respiration growth water model
Platform: UNKNOWN
Classifier: Development Status :: 5 - Production/Stable
Classifier: Intended Audience :: Science/Research
Classifier: Intended Audience :: Education
Classifier: Topic :: Scientific/Engineering
Classifier: License :: OSI Approved :: MIT License
Classifier: Programming Language :: Python :: 3.5
Requires-Python: >=3.5
